{"region_id": "myrtle-beach", "updated": "June 20, 2026 at 12:00 PM ET", "best_bet": {"county": "Horry County", "reason": "Horry's getting the slightly better wave action at 1 to 3 feet with that southeast wind, and the higher end of the water temp means the ocean feels genuinely inviting right now."}, "counties": [{"name": "Horry County", "risk": "MODERATE", "beaches": "Myrtle Beach \u00b7 North Myrtle Beach \u00b7 Surfside Beach \u00b7 Garden City"}, {"name": "Georgetown County", "risk": "MODERATE", "beaches": "Pawleys Island \u00b7 Litchfield Beach \u00b7 Huntington Beach State Park"}]}